process_data/__init__.py
process_data/setup.py
process_data-0.2.dist-info/METADATA
process_data-0.2.dist-info/WHEEL
process_data-0.2.dist-info/top_level.txt
process_data-0.2.dist-info/RECORD
