Metadata-Version: 2.1
Name: process-data
Version: 0.2
Summary: Data processing for the SEAT mobility advisor project
Home-page: UNKNOWN
Author: bauer2488
Author-email: UNKNOWN
License: MIT
Platform: UNKNOWN
